{"SubTexture":[{"y":97,"frameX":-1,"frameHeight":18,"frameY":-1,"width":51,"frameWidth":52,"height":17,"name":"yingzi","x":204},{"width":45,"y":175,"height":32,"name":"weiba","x":281},{"width":32,"y":84,"height":13,"name":"shoubi-z","x":301},{"y":234,"frameX":-1,"frameHeight":22,"frameY":-1,"width":29,"frameWidth":30,"height":21,"name":"shou-z","x":80},{"y":129,"frameX":-1,"frameHeight":118,"frameY":-1,"width":77,"frameWidth":78,"height":117,"name":"guancai3","x":1},{"y":1,"frameX":-1,"frameHeight":118,"frameY":-1,"width":77,"frameWidth":78,"height":117,"name":"guancai2","x":78},{"y":120,"frameX":-1,"frameHeight":113,"frameY":-1,"width":49,"frameWidth":50,"height":112,"name":"guancai1","x":80},{"width":44,"y":1,"height":41,"name":"pifeng2","x":199},{"width":78,"y":120,"height":53,"name":"pifeng1","x":209},{"y":1,"frameX":-1,"frameHeight":127,"frameY":-1,"width":75,"frameWidth":76,"height":126,"name":"wuqi","x":1},{"width":19,"y":149,"height":14,"name":"qun4","x":314},{"width":22,"y":103,"height":23,"name":"tui","x":289},{"width":20,"y":146,"height":9,"name":"jiao","x":335},{"y":124,"frameX":-1,"frameHeight":21,"frameY":-1,"width":10,"frameWidth":11,"height":20,"name":"qun3","x":331},{"y":189,"frameX":-1,"frameHeight":19,"frameY":-1,"width":6,"frameWidth":7,"height":18,"name":"qun2","x":338},{"y":189,"frameX":-1,"frameHeight":17,"frameY":-1,"width":8,"frameWidth":9,"height":16,"name":"qun1","x":328},{"y":112,"frameX":-1,"frameHeight":11,"frameY":-1,"width":21,"frameWidth":22,"height":10,"name":"yaodai","x":313},{"y":97,"frameX":-1,"frameHeight":5,"frameY":-1,"width":13,"frameWidth":14,"height":4,"name":"shenti","x":257},{"y":103,"frameX":-1,"frameHeight":15,"frameY":-1,"width":23,"frameWidth":24,"height":14,"name":"xiong","x":257},{"y":98,"frameX":-1,"frameHeight":20,"frameY":-1,"width":40,"frameWidth":41,"height":19,"name":"bozi","x":157},{"width":82,"y":191,"height":57,"name":"erduo","x":131},{"y":120,"frameX":-1,"frameHeight":70,"frameY":-1,"width":76,"frameWidth":77,"height":69,"name":"tou","x":131},{"y":155,"frameX":-1,"frameHeight":17,"frameY":-1,"width":23,"frameWidth":24,"height":16,"name":"zui-zc","x":289},{"y":128,"frameX":-1,"frameHeight":20,"frameY":-1,"width":20,"frameWidth":21,"height":19,"name":"zui-gj","x":309},{"width":18,"y":248,"height":7,"name":"zui-kh2","x":1},{"y":99,"frameX":-1,"frameHeight":12,"frameY":-1,"width":21,"frameWidth":22,"height":11,"name":"zui-kh1","x":313},{"y":210,"frameX":-1,"frameHeight":34,"frameY":-1,"width":62,"frameWidth":63,"height":33,"name":"yangjing-zc","x":215},{"y":175,"frameX":-1,"frameHeight":34,"frameY":-1,"width":64,"frameWidth":65,"height":33,"name":"yangjing-gj","x":215},{"y":210,"frameX":-1,"frameHeight":34,"frameY":-1,"width":62,"frameWidth":63,"height":33,"name":"yangjing-dj","x":279},{"y":165,"frameX":-1,"frameHeight":9,"frameY":-1,"width":31,"frameWidth":32,"height":8,"name":"meimao","x":314},{"y":53,"frameX":-1,"frameHeight":44,"frameY":-1,"width":45,"frameWidth":46,"height":43,"name":"toukui6","x":157},{"y":1,"frameX":-1,"frameHeight":54,"frameY":-1,"width":25,"frameWidth":26,"height":53,"name":"toukui5","x":277},{"y":56,"frameX":-1,"frameHeight":46,"frameY":-1,"width":22,"frameWidth":23,"height":45,"name":"toukui4","x":277},{"y":44,"frameX":-1,"frameHeight":51,"frameY":-1,"width":36,"frameWidth":37,"height":50,"name":"toukui3","x":204},{"y":44,"frameX":-1,"frameHeight":52,"frameY":-1,"width":33,"frameWidth":34,"height":51,"name":"toukui2","x":242},{"width":25,"y":1,"height":37,"name":"shou-y","x":245},{"y":1,"frameX":-1,"frameHeight":51,"frameY":-1,"width":40,"frameWidth":41,"height":50,"name":"toukui1","x":157},{"y":128,"frameX":-1,"frameHeight":26,"frameY":-1,"width":18,"frameWidth":19,"height":25,"name":"shou-kh3","x":289},{"y":56,"frameX":-1,"frameHeight":27,"frameY":-1,"width":19,"frameWidth":20,"height":26,"name":"shou-kh2","x":301},{"y":175,"frameX":-1,"frameHeight":13,"frameY":-1,"width":12,"frameWidth":13,"height":12,"name":"shou-kh1","x":328},{"y":234,"frameX":-3,"frameHeight":15,"frameY":-1,"width":16,"frameWidth":21,"height":13,"name":"wuqi-guang","x":111}],"width":512,"imagePath":"aijiyanhou_tex.png","height":256,"name":"aijiyanhou"}