{"imagePath":"head_20_tex.png","width":1024,"height":512,"name":"head_20","SubTexture":[{"width":94,"y":1,"height":94,"name":"kuang","x":889},{"width":45,"y":97,"height":46,"name":"aixin","x":889},{"width":26,"y":101,"height":16,"name":"yun2","x":976},{"width":17,"y":57,"height":11,"name":"yun1","x":998},{"width":38,"y":1,"height":54,"name":"renwu","x":985},{"width":11,"y":57,"height":42,"name":"gong","x":985},{"width":7,"y":70,"height":8,"name":"shouzhi","x":998},{"width":38,"y":97,"height":12,"name":"jian","x":936},{"frameY":-2,"y":311,"frameWidth":150,"frameHeight":155,"width":146,"height":153,"name":"xx/xx_09","frameX":-4,"x":1},{"frameY":-2,"y":311,"frameWidth":150,"frameHeight":155,"width":146,"height":153,"name":"xx/xx_14","frameX":-4,"x":297},{"frameY":-2,"y":156,"frameWidth":150,"frameHeight":155,"width":146,"height":153,"name":"xx/xx_03","frameX":-4,"x":445},{"frameY":-2,"y":156,"frameWidth":150,"frameHeight":155,"width":146,"height":153,"name":"xx/xx_15","frameX":-4,"x":1},{"frameY":-2,"y":311,"frameWidth":150,"frameHeight":155,"width":146,"height":153,"name":"xx/xx_02","frameX":-4,"x":149},{"frameY":-2,"y":311,"frameWidth":150,"frameHeight":155,"width":146,"height":153,"name":"xx/xx_13","frameX":-4,"x":593},{"frameY":-2,"y":311,"frameWidth":150,"frameHeight":155,"width":146,"height":153,"name":"xx/xx_08","frameX":-4,"x":445},{"frameY":-2,"y":1,"frameWidth":150,"frameHeight":155,"width":146,"height":153,"name":"xx/xx_00","frameX":-4,"x":445},{"frameY":-2,"y":1,"frameWidth":150,"frameHeight":155,"width":146,"height":153,"name":"xx/xx_01","frameX":-4,"x":741},{"frameY":-2,"y":1,"frameWidth":150,"frameHeight":155,"width":146,"height":153,"name":"xx/xx_07","frameX":-4,"x":593},{"frameY":-2,"y":156,"frameWidth":150,"frameHeight":155,"width":146,"height":153,"name":"xx/xx_12","frameX":-4,"x":593},{"frameY":-2,"y":1,"frameWidth":150,"frameHeight":155,"width":146,"height":153,"name":"xx/xx_04","frameX":-4,"x":149},{"frameY":-2,"y":156,"frameWidth":150,"frameHeight":155,"width":146,"height":153,"name":"xx/xx_11","frameX":-4,"x":149},{"frameY":-2,"y":156,"frameWidth":150,"frameHeight":155,"width":146,"height":153,"name":"xx/xx_06","frameX":-4,"x":297},{"frameY":-2,"y":1,"frameWidth":150,"frameHeight":155,"width":146,"height":153,"name":"xx/xx_05","frameX":-4,"x":297},{"frameY":-2,"y":1,"frameWidth":150,"frameHeight":155,"width":146,"height":153,"name":"xx/xx_10","frameX":-4,"x":1}]}