{"frameRate":30,"name":"jiushengyuan","version":"5.5","compatibleVersion":"5.5","armature":[{"type":"Armature","frameRate":30,"name":"armatureName","aabb":{"x":-43.39,"y":-120.71,"width":141.89,"height":129.41},"bone":[{"name":"root"},{"length":10.5,"name":"231","parent":"root","transform":{"x":-3.55,"y":-17.275,"skX":0.805,"skY":0.805}},{"name":"zong","parent":"root","transform":{"scX":0.9,"scY":0.9}},{"length":10,"name":"20","parent":"231","transform":{"x":9.35955,"y":2.39375,"skX":97.024,"skY":97.024}},{"length":9,"name":"31","parent":"231","transform":{"x":-0.3001,"y":3.55455,"skX":99.7664,"skY":99.7664}},{"name":"23","parent":"zong","transform":{"x":1.645,"y":-21.37}},{"length":5,"name":"22","parent":"23","transform":{"x":0.535,"y":-2.26,"skX":-82.23,"skY":-82.23}},{"length":16,"name":"28","parent":"23","transform":{"x":-3.41,"y":-2.77,"skX":166.5,"skY":166.5}},{"length":18,"name":"bone","parent":"22","transform":{"x":5.22,"skX":-13.19,"skY":-13.19}},{"length":16,"name":"bone3","parent":"28","transform":{"x":16.225,"skX":39.06,"skY":39.06}},{"length":32.5,"name":"21","parent":"bone","transform":{"x":18.24,"y":0.185,"skX":9.09,"skY":9.09}},{"length":17.5,"name":"hand","parent":"bone","transform":{"x":12.76,"y":3.6,"skX":95.83,"skY":95.83}},{"length":13.5,"name":"bone4","parent":"bone3","transform":{"x":16.085,"skX":52.35,"skY":52.35}},{"length":15.5,"name":"hand1","parent":"bone","transform":{"x":16.02,"y":-9.645,"skX":-145.32,"skY":-145.32}},{"name":"07","parent":"21","transform":{"x":57.99,"y":7.78}},{"length":14,"name":"bone7","parent":"21","transform":{"x":49.33,"y":24.76,"skX":35.2,"skY":35.2}},{"length":18,"name":"bone2","parent":"hand","transform":{"x":17.995,"y":0.195,"skX":1.59,"skY":1.59}},{"length":16,"name":"bone30","parent":"hand1","transform":{"x":15.535,"skX":-2.77,"skY":-2.77}},{"length":16,"name":"bone5","parent":"21","transform":{"x":43.725,"y":-26.84,"skX":-33.79,"skY":-33.79}},{"length":15.5,"name":"bone8","parent":"bone7","transform":{"x":14.195,"skX":-9.27,"skY":-9.27}},{"length":9,"name":"24","parent":"bone2","transform":{"x":18.3,"y":0.15,"skX":0.92,"skY":0.92}},{"length":17.5,"name":"bone6","parent":"bone5","transform":{"x":16.02,"skX":8.26,"skY":8.26}},{"length":24.5,"name":"wuqi3","parent":"bone30","transform":{"x":24.635,"y":-3.88,"skX":-16.92,"skY":-16.92}},{"length":17,"name":"paopao2","parent":"wuqi3","transform":{"x":110.15,"y":-11.295,"skX":-11.96,"skY":-11.96}},{"length":14,"name":"wuqi","parent":"24","transform":{"x":3.575,"y":-2.955,"skX":-57.23,"skY":-57.23}},{"length":17,"name":"paopao","parent":"wuqi","transform":{"x":41.87,"y":22.335,"skX":25.53,"skY":25.53}}],"slot":[{"name":"29","parent":"zong"},{"name":"28","parent":"28"},{"name":"hand","parent":"hand"},{"displayIndex":-1,"name":"wuqi3","parent":"wuqi3"},{"name":"wuqi2","parent":"wuqi"},{"name":"wuqi1","parent":"wuqi"},{"displayIndex":1,"name":"24","parent":"24"},{"name":"20","parent":"20"},{"name":"31","parent":"31"},{"name":"23","parent":"231"},{"name":"22","parent":"bone"},{"name":"21","parent":"21"},{"displayIndex":1,"name":"19","parent":"hand1"},{"displayIndex":1,"name":"18","parent":"hand1"},{"displayIndex":1,"name":"09","parent":"21"},{"displayIndex":1,"name":"08","parent":"21"},{"name":"07","parent":"07"},{"displayIndex":-1,"name":"03","parent":"bone30"},{"displayIndex":-1,"name":"paopao","parent":"paopao"},{"displayIndex":-1,"name":"paopao2","parent":"paopao2"}],"skin":[{"slot":[{"name":"wuqi3","display":[{"name":"wuqi3","transform":{"x":31.64,"y":-4.36,"skX":1.12,"skY":1.12}}]},{"name":"09","display":[{"name":"09","transform":{"x":17.39,"y":5.72,"skX":88.33,"skY":88.33}},{"name":"15","transform":{"x":24.64,"y":5.26,"skX":88.33,"skY":88.33}}]},{"name":"24","display":[{"name":"05","transform":{"x":3.82,"y":-1.45,"skX":-0.92,"skY":-0.92}},{"name":"24","transform":{"x":5.07,"y":-1.39,"skX":-0.92,"skY":-0.92}}]},{"name":"wuqi1","display":[{"name":"wuqi1","transform":{"x":22.36,"y":4.88,"skX":56.31,"skY":56.31}}]},{"name":"wuqi2","display":[{"name":"wuqi2","transform":{"x":23.46,"y":7.45,"skX":56.31,"skY":56.31}}]},{"name":"22","display":[{"name":"22","transform":{"x":7.23,"y":1.25,"skX":97.42,"skY":97.42}}]},{"name":"paopao2","display":[{"name":"paopao","transform":{"x":31.96,"y":-3.03,"skX":30.78,"skY":30.78}}]},{"name":"23","display":[{"type":"mesh","name":"23","width":20,"height":15,"vertices":[-7.35,-24.17,-5.77,-31.26,3.56,-30.98,11.95,-30.68,11.8,-23.31,11.8,-19.15,11.8,-13.82,-0.03,-13.82,-8.7,-13.82,-8.7,-19.58,2.27,-23.89,0.83,-18.86],"uvs":[0.06574,0.31025,0.12174,0,0.59074,0,1,0,1,0.36765,1,0.64509,1,1,0.42274,1,0,1,0,0.61639,0.53474,0.32939,0.46474,0.66422],"triangles":[2,10,4,2,4,3,4,10,5,10,11,5,5,11,6,11,7,6,1,10,2,0,11,10,1,0,10,9,8,7,9,7,11,0,9,11],"weights":[1,5,1,1,8,1,1,8,1,1,8,1,1,5,1,1,5,1,1,5,1,1,5,1,1,5,1,1,5,1,1,5,1,1,5,1],"slotPose":[1,0,0,1,0,0],"bonePose":[5,1,0,0,1,1.645,-21.37,8,-0.129142,-0.991626,0.991626,-0.129142,3.244794,-28.740246],"edges":[8,7,7,6,6,5,5,4,4,3,3,2,2,1,1,0,0,9,9,8],"userEdges":[]}]},{"name":"03","display":[{"name":"03","transform":{"x":12.53,"y":1.38,"skX":-18.58,"skY":-18.58}}]},{"name":"18","display":[{"name":"02","transform":{"x":-0.26,"y":9.2,"skX":-117.26,"skY":-117.26}},{"name":"18","transform":{"x":4.88,"y":8.24,"skX":-117.26,"skY":-117.26}}]},{"name":"20","display":[{"name":"20","transform":{"x":4.01,"y":4.77,"skX":-98.11,"skY":-98.11,"scX":0.9,"scY":0.9}}]},{"name":"hand","display":[{"type":"mesh","name":"hand","width":43,"height":16,"vertices":[3.3,-46.85,3.31,-37.82,8.49,-37.82,15.39,-37.82,22.29,-37.82,29.93,-37.83,34.37,-37.83,40.04,-37.83,44.23,-37.83,46.8,-43.4,46.8,-53.51,38.56,-53.82,30.92,-53.83,24.51,-53.02,17.36,-51.04,10.46,-48.83],"uvs":[0,0.43563,0,1,0.1192,1,0.27787,1,0.43653,1,0.6122,1,0.7142,1,0.84453,1,0.94087,1,1,0.65132,1,0.01966,0.81053,0,0.63487,0,0.48753,0.05047,0.3232,0.17372,0.16453,0.31238],"triangles":[7,8,9,11,7,9,10,11,9,11,6,7,12,5,6,12,6,11,13,5,12,13,4,5,14,4,13,14,3,4,15,3,14,15,2,3,0,1,2,0,2,15],"weights":[1,11,1,1,11,1,2,11,0.99431,16,0.00569,1,11,1,2,11,0.47384,16,0.52616,1,16,1,1,16,1,2,11,0.01173,16,0.98827,1,16,1,2,11,0.00001,16,0.99999,2,11,0.01566,16,0.98434,2,11,0.08707,16,0.91293,2,11,0.27244,16,0.72756,2,11,0.55451,16,0.44549,2,11,0.91339,16,0.08661,2,11,0.99966,16,0.00034],"slotPose":[1,0,0,1,0,0],"bonePose":[11,0.999615,-0.027747,0.027747,0.999615,5.166799,-41.858306,16,1,0,0,1,23.160281,-42.162691],"edges":[0,1,1,2,2,3,3,4,4,5,5,6,6,7,7,8,8,9,9,10,10,11,11,12,12,13,13,14,14,15,15,0],"userEdges":[13,4,12,5,11,7,15,2]}]},{"name":"08","display":[{"name":"08","transform":{"x":6.83,"y":3.53,"skX":88.33,"skY":88.33}},{"name":"13","transform":{"x":10.29,"y":10.93,"skX":88.33,"skY":88.33}}]},{"name":"07","display":[{"name":"07","transform":{"x":-5.71,"y":-6.58,"skX":88.33,"skY":88.33}}]},{"name":"29","display":[{"name":"29","transform":{"x":3.81,"y":-0.33}}]},{"name":"paopao","display":[{"name":"paopao","transform":{"x":31.96,"y":-3.03,"skX":30.78,"skY":30.78}}]},{"name":"21","display":[{"type":"mesh","name":"21","width":94,"height":83,"vertices":[-43.12,-83.09,-44.87,-90.75,-46.39,-100.8,-46.61,-109.54,-46.39,-117.84,-45.95,-124.55,-35.91,-124.55,-26.95,-121.11,-20.61,-117.62,-14.05,-114.12,-8.81,-110.19,-0.29,-112.38,8.45,-111.72,14.57,-109.97,20.25,-113.9,25.71,-117.18,31.39,-120.02,38.38,-123.08,44.94,-124.39,47.3,-119.36,47.3,-111.72,47.3,-104.51,47.3,-97.08,45.59,-88.78,43.41,-83.09,47.3,-82.22,47.3,-75,43.85,-70.64,47.3,-67.8,47.3,-59.27,43.84,-51.84,36.63,-46.6,28.33,-42.67,17.63,-41.04,8.01,-41.04,-3.13,-41.04,-13.62,-43.55,-23.89,-46.17,-30.88,-51.2,-37.88,-56.66,-40.49,-65.61,-44.65,-69.33,-47.2,-74.79,-47.2,-81.78,-34.77,-79,-25.96,-85.33,-17.87,-93.78,-11.54,-100.82,-32.13,-93.25,-22.45,-103.11,-35.99,-102.94,-28.6,-110.5,-37.76,-115.43,-41.1,-121.06,36.52,-91.84,25.25,-101.7,35.46,-106.81,39.51,-114.19,42.49,-119.65],"uvs":[0.04322,0.49375,0.02472,0.40478,0.00853,0.28441,0.00622,0.17974,0.00853,0.0803,0.01316,0,0.11952,0,0.21432,0.04105,0.28137,0.08292,0.35073,0.12479,0.40623,0.17189,0.4964,0.14572,0.58889,0.15357,0.65363,0.1745,0.71374,0.1274,0.77155,0.08815,0.83166,0.05413,0.90565,0.0175,0.97502,0.0018,1,0.06198,1,0.15357,1,0.23992,1,0.32889,0.98196,0.42833,0.95883,0.49637,1,0.50683,1,0.59319,0.96346,0.64552,1,0.67954,1,0.78159,0.96346,0.87056,0.88716,0.93337,0.79929,0.98047,0.686,1,0.58426,1,0.46634,1,0.35536,0.97,0.24669,0.9386,0.1727,0.87841,0.09871,0.81299,0.07096,0.70571,0.02703,0.66122,0,0.5958,0,0.51207,0.13158,0.54479,0.2247,0.46905,0.31037,0.36805,0.37742,0.28387,0.15952,0.37455,0.26195,0.25656,0.11854,0.25869,0.19676,0.16811,0.09992,0.10912,0.06453,0.04169,0.88586,0.39158,0.76667,0.27355,0.87469,0.21242,0.91753,0.12389,0.94919,0.05855],"triangles":[57,56,21,54,23,22,21,56,22,56,54,22,18,58,19,57,21,20,19,58,20,58,57,20,24,27,26,24,26,25,28,27,29,27,30,29,27,31,30,54,24,23,32,31,27,17,58,18,54,34,27,34,33,27,33,32,27,54,27,24,17,57,58,46,34,55,55,34,54,56,55,54,17,16,57,16,56,57,16,15,56,47,46,55,15,55,56,46,35,34,14,55,15,13,47,55,45,36,35,46,45,35,12,47,13,14,13,55,11,47,12,45,37,36,44,38,45,45,38,37,10,47,11,44,40,38,9,49,47,9,47,10,40,39,38,49,46,47,8,49,9,51,49,8,49,48,46,48,45,46,7,51,8,51,50,49,50,48,49,52,51,7,48,44,45,6,52,7,0,44,48,52,50,51,41,40,44,1,0,48,53,52,6,50,1,48,2,1,50,52,3,50,0,42,44,42,41,44,3,2,50,5,53,6,53,4,52,4,3,52,43,42,0,5,4,53],"weights":[1,10,1,2,18,0.90782,21,0.09218,2,18,0.47766,21,0.52234,2,18,0.05863,21,0.94137,1,21,1,1,21,1,3,15,0.00009,18,0.00147,21,0.99844,3,15,0.00582,18,0.12129,21,0.87289,3,15,0.02518,18,0.38555,21,0.58927,3,15,0.07587,18,0.62853,21,0.29559,1,10,1,1,10,1,1,10,1,1,10,1,3,15,0.72203,19,0.24262,18,0.03535,3,15,0.43714,19,0.55303,18,0.00983,3,15,0.12363,19,0.87485,18,0.00152,2,15,0.00095,19,0.99905,1,19,1,1,19,1,2,15,0.02353,19,0.97647,2,15,0.34879,19,0.65121,2,15,0.77561,19,0.22439,2,15,0.96608,19,0.03392,1,10,1,1,10,1,1,10,1,1,10,1,1,10,1,1,10,1,1,10,1,1,10,1,1,10,1,1,10,1,1,10,1,1,10,1,1,10,1,1,10,1,1,10,1,1,10,1,1,10,1,1,10,1,1,10,1,1,10,1,1,10,1,1,10,1,1,10,1,1,10,1,2,18,0.9976,21,0.0024,3,15,0.02232,18,0.86794,21,0.10974,2,18,0.56648,21,0.43352,3,15,0.0062,18,0.27852,21,0.71528,1,21,1,1,21,1,1,10,1,1,10,1,3,15,0.5573,19,0.44267,18,0.00003,2,15,0.00018,19,0.99981,1,19,1],"slotPose":[1,0,0,1,0,0],"bonePose":[10,0.029143,-0.999575,0.999575,0.029143,1.072699,-46.851398,18,-0.531694,-0.846936,0.846936,-0.531694,-24.481629,-91.340021,21,-0.404503,-0.914537,0.914537,-0.404503,-32.99937,-104.907942,15,0.600001,-0.799999,0.799999,0.600001,27.2598,-95.438868,19,0.463296,-0.886204,0.886204,0.463296,35.776821,-106.794853],"edges":[42,41,41,40,40,39,39,38,38,37,37,36,36,35,35,34,34,33,33,32,32,31,31,30,30,29,29,28,28,27,27,26,26,25,25,24,24,23,23,22,22,21,21,20,20,19,19,18,18,17,17,16,16,15,15,14,14,13,13,12,12,11,11,10,10,9,9,8,8,7,7,6,6,5,5,4,4,3,3,2,2,1,1,0,0,43,43,42],"userEdges":[]}]},{"name":"28","display":[{"type":"mesh","name":"28","width":45,"height":35,"vertices":[2.3,-27.45,2.3,-22.45,-1.42,-18.75,-5.83,-15.76,-10.68,-12.48,-17.94,-10.82,-25.07,-10.82,-30.77,-10.82,-35.9,-12.34,-39.6,-16.18,-42.45,-20.32,-43.2,-25.16,-43.2,-31.43,-41.02,-38.27,-37.6,-42.69,-33.9,-45.82,-28.2,-45.83,-26.91,-41.84,-25.78,-37.99,-22.5,-33.71,-18.37,-30.43,-13.38,-28.44,-8.25,-27.45,-2.98,-27.59,-32.05,-40.84,-32.48,-34.85,-31.76,-28.02,-26.35,-23.32,-17.09,-20.32,-8.68,-21.6,-1.98,-23.74],"uvs":[1,0.52516,1,0.66766,0.91841,0.77352,0.82132,0.85902,0.71484,0.95266,0.55511,1,0.39852,1,0.27324,1,0.16049,0.95673,0.07907,0.84681,0.01643,0.72873,0,0.59031,0,0.41116,0.04775,0.21573,0.12291,0.08952,0.20434,0,0.32962,0,0.3578,0.11395,0.38286,0.22388,0.45489,0.34602,0.54571,0.43966,0.65533,0.49666,0.76808,0.52516,0.88396,0.52109,0.24506,0.14245,0.23566,0.31345,0.25132,0.50888,0.37033,0.64323,0.5739,0.72873,0.75868,0.69209,0.90588,0.63102],"triangles":[30,2,1,30,1,0,23,30,0,30,29,2,29,3,2,23,22,30,22,29,30,29,4,3,28,4,29,21,29,22,21,28,29,28,5,4,20,28,21,6,5,28,27,6,28,20,27,28,19,27,20,27,7,6,26,27,19,18,25,19,25,26,19,8,7,27,9,8,27,17,24,18,24,25,18,26,9,27,16,24,17,15,24,16,10,9,26,11,10,26,14,13,25,25,12,26,12,11,26,14,25,24,15,14,24,13,12,25],"weights":[2,7,0.99869,9,0.00131,1,7,1,2,7,0.99453,9,0.00547,2,7,0.92843,9,0.07157,2,7,0.75646,9,0.24354,3,7,0.48433,9,0.51526,12,0.00041,3,7,0.22235,9,0.7713,12,0.00635,3,7,0.061,9,0.90458,12,0.03442,3,7,0.00527,9,0.88354,12,0.11119,3,7,0.00001,9,0.74213,12,0.25786,2,9,0.53146,12,0.46854,2,9,0.30828,12,0.69172,2,9,0.13041,12,0.86959,2,9,0.03583,12,0.96417,2,9,0.00295,12,0.99705,2,9,0.00322,12,0.99678,3,7,0.00001,9,0.02415,12,0.97584,3,7,0.00277,9,0.10936,12,0.88787,3,7,0.03092,9,0.26605,12,0.70303,3,7,0.14273,9,0.41419,12,0.44307,3,7,0.35885,9,0.43476,12,0.20639,3,7,0.63529,9,0.30337,12,0.06134,3,7,0.85549,9,0.13561,12,0.00891,3,7,0.96995,9,0.02972,12,0.00033,2,9,0.0048,12,0.9952,2,9,0.01312,12,0.98688,2,9,0.16556,12,0.83444,1,9,1,2,7,0.90638,9,0.09362,1,7,1,1,7,1],"slotPose":[1,0,0,1,0,0],"bonePose":[7,-0.97237,0.233445,-0.233445,-0.97237,-1.765,-24.14,9,-0.902134,-0.431456,0.431456,-0.902134,-17.541702,-20.352349,12,-0.209448,-0.97782,0.97782,-0.209448,-32.052527,-27.292319],"edges":[11,10,10,9,9,8,8,7,7,6,6,5,5,4,4,3,3,2,2,1,1,0,0,23,23,22,22,21,21,20,20,19,19,18,18,17,17,16,16,15,15,14,14,13,13,12,12,11],"userEdges":[]}]},{"name":"19","display":[{"name":"04","transform":{"x":9.38,"y":1.7,"skX":-117.26,"skY":-117.26}},{"type":"mesh","name":"19","width":25,"height":40,"vertices":[-12.96,-44.82,-17.79,-40.36,-20.69,-33.84,-24.55,-25.15,-29.63,-22.01,-31.2,-15.73,-31.19,-8.72,-26.73,-4.32,-18.75,-4.32,-11.03,-5.59,-7.64,-12.35,-9.1,-21.77,-6.68,-30.95,-6.42,-38.27,-6.2,-44.82,-20.45,-14.29,-17.3,-23.21,-13.45,-33.12,-11.27,-39.4],"uvs":[0.72936,0,0.53616,0.11007,0.42024,0.27107,0.26568,0.48574,0.06282,0.56326,0,0.71829,0,0.89122,0.17874,1,0.49752,1,0.80664,0.96874,0.94188,0.80178,0.88392,0.56922,0.98052,0.34263,0.99081,0.16166,1,0,0.4299,0.75407,0.55548,0.53344,0.71004,0.28896,0.79698,0.13392],"triangles":[17,11,12,0,18,14,17,12,13,18,17,13,14,18,13,17,16,11,11,15,10,16,15,11,15,9,10,1,17,18,0,1,18,15,8,9,2,16,17,1,2,17,15,7,8,3,15,16,2,3,16,3,4,15,6,7,15,5,6,15,4,5,15],"weights":[1,13,1,2,13,0.99983,17,0.00017,2,13,0.69496,17,0.30504,2,13,0.00048,17,0.99952,1,17,1,1,17,1,1,17,1,1,17,1,1,17,1,1,17,1,1,17,1,2,13,0.08654,17,0.91346,2,13,0.88074,17,0.11926,1,13,1,1,13,1,1,17,1,1,17,1,2,13,0.99952,17,0.00048,1,13,1],"slotPose":[1,0,0,1,0,0],"bonePose":[13,-0.458029,0.888937,-0.888937,-0.458029,-8.388291,-43.380525,17,-0.414534,0.910034,-0.910034,-0.414534,-15.503773,-29.570885],"edges":[5,6,6,7,7,8,8,9,9,10,10,11,11,12,12,13,13,14,14,0,0,1,1,2,2,3,3,4,4,5],"userEdges":[11,15,10,15]}]},{"name":"31","display":[{"name":"31","transform":{"x":5.58,"y":-1.04,"skX":-100.57,"skY":-100.57}}]}]}],"animation":[{"duration":12,"name":"attack_1","bone":[{"name":"22","rotateFrame":[{"tweenEasing":0},{"duration":7,"curve":[0.25,0,0.75,1],"rotate":-2.16},{"duration":4,"curve":[0.25,0,0.75,1],"rotate":0.58},{"duration":0}]},{"name":"bone","translateFrame":[{"duration":2,"curve":[0,0,0.75,1]},{"duration":7,"curve":[0.25,0,0.75,1],"x":0.49,"y":-0.1},{"duration":3,"curve":[0.25,0,0.75,1],"x":-0.49,"y":0.1},{"duration":0}],"rotateFrame":[{"duration":2,"curve":[0,0,0.75,1]},{"duration":7,"curve":[0.25,0,0.75,1],"rotate":-2.51},{"duration":3,"curve":[0.25,0,0.75,1],"rotate":2},{"duration":0}]},{"name":"hand","rotateFrame":[{"duration":2,"curve":[0.25,0,0.75,1]},{"duration":8,"curve":[0.25,0,0.75,1],"rotate":26.59},{"duration":2}]},{"name":"bone2","rotateFrame":[{"duration":2,"curve":[0.25,0,0.75,1]},{"duration":8,"curve":[0.25,0,0.75,1],"rotate":-57.64},{"duration":2}]},{"name":"21","translateFrame":[{"duration":2,"curve":[0.25,0,0.75,1]},{"duration":3,"curve":[0.25,0,0.75,1],"x":-0.48,"y":-0.12},{"duration":7,"curve":[0.25,0,0.75,1],"x":1.48,"y":0.28},{"duration":0}],"rotateFrame":[{"duration":2,"curve":[0.25,0,0.75,1]},{"duration":3,"curve":[0.25,0,0.75,1],"rotate":1.67},{"duration":7,"curve":[0.25,0,0.75,1],"rotate":-6.67},{"duration":0}]},{"name":"hand1","rotateFrame":[{"duration":2,"tweenEasing":0},{"duration":10,"tweenEasing":0,"rotate":16.94},{"duration":0}]},{"name":"bone30","rotateFrame":[{"duration":2,"tweenEasing":0},{"duration":3,"tweenEasing":0,"rotate":-17.67},{"duration":7,"tweenEasing":0,"rotate":-0.29},{"duration":0}]},{"name":"28","rotateFrame":[{"duration":2,"curve":[0.25,0,0.75,1]},{"duration":10,"curve":[0.25,0,0.75,1],"rotate":-5.55},{"duration":0}]},{"name":"bone3","rotateFrame":[{"duration":2,"curve":[0.25,0,0.75,1]},{"duration":2,"curve":[0.25,0,0.75,1],"rotate":5.32},{"duration":8,"curve":[0.25,0,0.75,1],"rotate":-9.01},{"duration":0}]},{"name":"bone4","rotateFrame":[{"duration":4,"curve":[0.25,0,0.75,1]},{"duration":3,"curve":[0.25,0,0.75,1],"rotate":13.81},{"duration":5,"curve":[0.25,0,0.75,1],"rotate":-21.91},{"duration":0}]},{"name":"07","translateFrame":[{"duration":3,"curve":[0.25,0,0.75,1]},{"duration":3,"curve":[0.25,0,0.75,1],"x":-1,"y":-0.06},{"duration":6,"curve":[0.25,0,0.75,1],"x":2.31,"y":0.23},{"duration":0}]},{"name":"bone5","rotateFrame":[{"curve":[0.25,0,0.75,1]},{"duration":5,"curve":[0.25,0,0.75,1],"rotate":5.4},{"duration":6,"curve":[0.25,0,0.75,1],"rotate":-2.56},{"duration":0}]},{"name":"bone6","rotateFrame":[{"duration":2,"curve":[0.25,0,0.75,1]},{"duration":6,"curve":[0.25,0,0.75,1],"rotate":10.19},{"duration":4,"curve":[0.25,0,0.75,1],"rotate":-10.56},{"duration":0}]},{"name":"bone7","rotateFrame":[{"curve":[0.25,0,0.75,1]},{"duration":5,"curve":[0.25,0,0.75,1],"rotate":6.07},{"duration":6,"curve":[0.25,0,0.75,1],"rotate":-7.28},{"duration":0}]},{"name":"bone8","rotateFrame":[{"duration":2,"curve":[0.25,0,0.75,1]},{"duration":4,"curve":[0.25,0,0.75,1],"rotate":7.72},{"duration":6,"curve":[0.25,0,0.75,1],"rotate":-16.22},{"duration":0}]}],"slot":[{"name":"08","displayFrame":[{"value":1},{"duration":6,"value":-1},{"duration":5,"value":1}]},{"name":"09","displayFrame":[{"value":1},{"duration":6},{"duration":5,"value":1}]}]},{"duration":15,"name":"attack_3","bone":[{"name":"22","rotateFrame":[{"tweenEasing":0},{"duration":8,"curve":[0.25,0,0.75,1],"rotate":-2.16},{"duration":6,"curve":[0.25,0,0.75,1],"rotate":0.58},{"duration":0}]},{"name":"bone","translateFrame":[{"duration":2,"curve":[0,0,0.75,1]},{"duration":8,"curve":[0.25,0,0.75,1],"x":0.49,"y":-0.1},{"duration":5,"curve":[0.25,0,0.75,1],"x":-0.49,"y":0.1},{"duration":0}],"rotateFrame":[{"duration":2,"curve":[0,0,0.75,1]},{"duration":8,"curve":[0.25,0,0.75,1],"rotate":-2.51},{"duration":5,"curve":[0.25,0,0.75,1],"rotate":2},{"duration":0}]},{"name":"hand","rotateFrame":[{"duration":2,"curve":[0.25,0,0.75,1],"rotate":30.48},{"duration":9,"curve":[0.25,0,0.75,1],"rotate":60},{"duration":4,"rotate":30.48}]},{"name":"bone2","rotateFrame":[{"duration":2,"curve":[0.25,0,0.75,1],"rotate":-5.59},{"duration":9,"curve":[0.25,0,0.75,1],"rotate":-68.46},{"duration":4,"curve":[0.25,0,0.75,1],"rotate":-3.07},{"duration":0,"rotate":-5.59}]},{"name":"24","translateFrame":[{"duration":15,"x":4.88,"y":0.86}],"rotateFrame":[{"duration":2,"tweenEasing":0,"rotate":-23.15},{"duration":9,"tweenEasing":0,"rotate":6.15},{"duration":4,"rotate":-23.15}]},{"name":"21","translateFrame":[{"duration":2,"curve":[0.25,0,0.75,1]},{"duration":3,"curve":[0.25,0,0.75,1],"x":-0.48,"y":-0.12},{"duration":10,"curve":[0.25,0,0.75,1],"x":1.48,"y":0.28},{"duration":0}],"rotateFrame":[{"duration":2,"curve":[0.25,0,0.75,1]},{"duration":3,"curve":[0.25,0,0.75,1],"rotate":1.67},{"duration":10,"curve":[0.25,0,0.75,1],"rotate":-6.67},{"duration":0}]},{"name":"hand1","rotateFrame":[{"duration":2,"curve":[0,0,0.75,1]},{"duration":9,"curve":[0.25,0,0.75,1],"rotate":21.08},{"duration":4,"curve":[0.25,0,0.75,1],"rotate":-1.66},{"duration":0}]},{"name":"bone30","rotateFrame":[{"duration":2,"curve":[0,0,0.75,1],"rotate":-98.31},{"duration":9,"curve":[0.25,0,0.75,1],"rotate":-124.57},{"duration":4,"curve":[0.25,0,0.75,1],"rotate":-97},{"duration":0,"rotate":-98.31}]},{"name":"28","rotateFrame":[{"duration":2,"curve":[0.25,0,0.75,1]},{"duration":13,"curve":[0.25,0,0.75,1],"rotate":-5.55},{"duration":0}]},{"name":"bone3","rotateFrame":[{"duration":2,"curve":[0.25,0,0.75,1]},{"duration":2,"curve":[0.25,0,0.75,1],"rotate":5.32},{"duration":11,"curve":[0.25,0,0.75,1],"rotate":-9.01},{"duration":0}]},{"name":"bone4","rotateFrame":[{"duration":4,"curve":[0.25,0,0.75,1]},{"duration":3,"curve":[0.25,0,0.75,1],"rotate":13.81},{"duration":8,"curve":[0.25,0,0.75,1],"rotate":-21.91},{"duration":0}]},{"name":"07","translateFrame":[{"duration":3,"curve":[0.25,0,0.75,1]},{"duration":3,"curve":[0.25,0,0.75,1],"x":-1,"y":-0.06},{"duration":5,"curve":[0.25,0,0.75,1],"x":4.37,"y":0.41},{"duration":4,"curve":[0.25,0,0.75,1],"x":-1.5,"y":0.04},{"duration":0}]},{"name":"bone5","rotateFrame":[{"curve":[0.25,0,0.75,1]},{"duration":5,"curve":[0.25,0,0.75,1],"rotate":5.4},{"duration":9,"curve":[0.25,0,0.75,1],"rotate":-2.56},{"duration":0}]},{"name":"bone6","rotateFrame":[{"duration":2,"curve":[0.25,0,0.75,1]},{"duration":6,"curve":[0.25,0,0.75,1],"rotate":10.19},{"duration":7,"curve":[0.25,0,0.75,1],"rotate":-10.56},{"duration":0}]},{"name":"bone7","rotateFrame":[{"curve":[0.25,0,0.75,1]},{"duration":5,"curve":[0.25,0,0.75,1],"rotate":6.07},{"duration":9,"curve":[0.25,0,0.75,1],"rotate":-7.28},{"duration":0}]},{"name":"bone8","rotateFrame":[{"duration":2,"curve":[0.25,0,0.75,1]},{"duration":4,"curve":[0.25,0,0.75,1],"rotate":7.72},{"duration":9,"curve":[0.25,0,0.75,1],"rotate":-16.22},{"duration":0}]}],"slot":[{"name":"03","displayFrame":[{"duration":15}]},{"name":"08","displayFrame":[{"value":1},{"duration":6,"value":-1},{"duration":8,"value":1}]},{"name":"09","displayFrame":[{"value":1},{"duration":6},{"duration":8,"value":1}]},{"name":"18","displayFrame":[{"duration":15}]},{"name":"19","displayFrame":[{"duration":15}]},{"name":"24","displayFrame":[{"duration":15}]},{"name":"wuqi1","displayFrame":[{"duration":15,"value":-1}]},{"name":"wuqi3","displayFrame":[{"duration":15}]},{"name":"wuqi2","displayFrame":[{"duration":15,"value":-1}]}],"zOrder":{"frame":[{"duration":15,"zOrder":[3,9,4,9,5,9,6,9]}]}},{"duration":30,"name":"idle_1_2","bone":[{"name":"bone","translateFrame":[{"duration":15,"curve":[0.25,0,0.75,1],"x":0.49,"y":-0.1},{"duration":15,"curve":[0.25,0,0.75,1]},{"duration":0,"x":0.49,"y":-0.1}],"rotateFrame":[{"duration":15,"curve":[0.25,0,0.75,1],"rotate":-2.33},{"duration":15,"curve":[0.25,0,0.75,1],"rotate":-0.99},{"duration":0,"rotate":-2.33}]},{"name":"hand","rotateFrame":[{"duration":15,"curve":[0.25,0,0.75,1],"rotate":-7.13},{"duration":15,"curve":[0.25,0,0.75,1],"rotate":-6.39},{"duration":0,"rotate":-7.13}]},{"name":"bone2","rotateFrame":[{"duration":7,"curve":[0,0,0.75,1],"rotate":-5.47},{"duration":15,"curve":[0.25,0,0.75,1],"rotate":-3.79},{"duration":8,"curve":[0.25,0,1,1],"rotate":-6.72},{"duration":0,"rotate":-5.47}]},{"name":"paopao","scaleFrame":[{"duration":8,"curve":[0.372,0.48,0.752,1],"x":0.76,"y":0.76},{"duration":15,"curve":[0.25,0,0.75,1],"x":0.47,"y":0.47},{"duration":7,"curve":[0.25,0,1,1]},{"duration":0,"x":0.76,"y":0.76}]},{"name":"21","rotateFrame":[{"duration":7,"curve":[0,0,0.75,1]},{"duration":16,"curve":[0.25,0,0.75,1],"rotate":-1.59},{"duration":7,"curve":[0.25,0,1,1],"rotate":0.85},{"duration":0}]},{"name":"hand1","rotateFrame":[{"duration":15,"curve":[0.25,0,0.75,1]},{"duration":15,"curve":[0.25,0,0.75,1],"rotate":-0.65},{"duration":0}]},{"name":"bone30","rotateFrame":[{"duration":5,"curve":[0,0,0.75,1]},{"duration":15,"curve":[0.25,0,0.75,1],"rotate":2.06},{"duration":10,"curve":[0.25,0,1,1],"rotate":-2.51},{"duration":0}]},{"name":"28","rotateFrame":[{"duration":15,"curve":[0.25,0,0.75,1]},{"duration":15,"curve":[0.25,0,0.75,1],"rotate":-2.59},{"duration":0}]},{"name":"bone3","rotateFrame":[{"duration":5,"curve":[0.382,0.57,0.735,1],"rotate":-2.17},{"duration":15,"curve":[0.25,0,0.75,1]},{"duration":10,"curve":[0.243,0,0.649,0.6],"rotate":-7.66},{"duration":0,"rotate":-2.17}]},{"name":"bone4","rotateFrame":[{"duration":10,"curve":[0.351,0.4,0.757,1],"rotate":-8.96},{"duration":15,"curve":[0.25,0,0.75,1]},{"duration":5,"curve":[0.265,0,0.618,0.43],"rotate":-12.51},{"duration":0,"rotate":-8.96}]},{"name":"bone5","rotateFrame":[{"duration":10,"curve":[0,0,0.75,1]},{"duration":15,"curve":[0.25,0,0.75,1],"rotate":-2.93},{"duration":5,"curve":[0.25,0,1,1],"rotate":0.97},{"duration":0}]},{"name":"bone6","rotateFrame":[{"duration":15,"curve":[0.25,0,0.75,1]},{"duration":15,"curve":[0.25,0,0.75,1],"rotate":-7.19},{"duration":0}]},{"name":"bone7","rotateFrame":[{"duration":10,"curve":[0,0,0.75,1]},{"duration":15,"curve":[0.25,0,0.75,1],"rotate":-3.61},{"duration":5,"curve":[0.25,0,1,1],"rotate":1.88},{"duration":0}]},{"name":"bone8","rotateFrame":[{"duration":15,"curve":[0.25,0,0.75,1]},{"duration":15,"curve":[0.25,0,0.75,1],"rotate":-9.48},{"duration":0}]}],"slot":[{"name":"08","displayFrame":[{"duration":30}]},{"name":"paopao","displayFrame":[{"duration":30}]}]},{"duration":30,"name":"idle_3_2","bone":[{"name":"bone","translateFrame":[{"duration":15,"curve":[0.25,0,0.75,1],"x":0.49,"y":-0.1},{"duration":15,"curve":[0.25,0,0.75,1]},{"duration":0,"x":0.49,"y":-0.1}],"rotateFrame":[{"duration":15,"curve":[0.25,0,0.75,1],"rotate":-2.33},{"duration":15,"curve":[0.25,0,0.75,1],"rotate":-0.99},{"duration":0,"rotate":-2.33}]},{"name":"hand","rotateFrame":[{"duration":30,"rotate":30.48}]},{"name":"bone2","rotateFrame":[{"duration":30,"rotate":-5.59}]},{"name":"24","translateFrame":[{"duration":30,"x":4.88,"y":0.86}],"rotateFrame":[{"duration":30,"rotate":-23.15}]},{"name":"paopao","scaleFrame":[{"duration":8,"curve":[0.372,0.48,0.752,1],"x":0.76,"y":0.76},{"duration":15,"curve":[0.25,0,0.75,1],"x":0.47,"y":0.47},{"duration":7,"curve":[0.25,0,1,1]},{"duration":0,"x":0.76,"y":0.76}]},{"name":"21","rotateFrame":[{"duration":7,"curve":[0,0,0.75,1]},{"duration":16,"curve":[0.25,0,0.75,1],"rotate":-1.59},{"duration":7,"curve":[0.25,0,1,1],"rotate":0.85},{"duration":0}]},{"name":"bone30","rotateFrame":[{"duration":30,"rotate":-78.23}]},{"name":"28","rotateFrame":[{"duration":15,"curve":[0.25,0,0.75,1]},{"duration":15,"curve":[0.25,0,0.75,1],"rotate":-2.59},{"duration":0}]},{"name":"bone3","rotateFrame":[{"duration":5,"curve":[0.382,0.57,0.735,1],"rotate":-2.17},{"duration":15,"curve":[0.25,0,0.75,1]},{"duration":10,"curve":[0.243,0,0.649,0.6],"rotate":-7.66},{"duration":0,"rotate":-2.17}]},{"name":"bone4","rotateFrame":[{"duration":10,"curve":[0.351,0.4,0.757,1],"rotate":-8.96},{"duration":15,"curve":[0.25,0,0.75,1]},{"duration":5,"curve":[0.265,0,0.618,0.43],"rotate":-12.51},{"duration":0,"rotate":-8.96}]},{"name":"bone5","rotateFrame":[{"duration":10,"curve":[0,0,0.75,1]},{"duration":15,"curve":[0.25,0,0.75,1],"rotate":-2.93},{"duration":5,"curve":[0.25,0,1,1],"rotate":0.97},{"duration":0}]},{"name":"bone6","rotateFrame":[{"duration":15,"curve":[0.25,0,0.75,1]},{"duration":15,"curve":[0.25,0,0.75,1],"rotate":-7.19},{"duration":0}]},{"name":"bone7","rotateFrame":[{"duration":10,"curve":[0,0,0.75,1]},{"duration":15,"curve":[0.25,0,0.75,1],"rotate":-3.61},{"duration":5,"curve":[0.25,0,1,1],"rotate":1.88},{"duration":0}]},{"name":"bone8","rotateFrame":[{"duration":15,"curve":[0.25,0,0.75,1]},{"duration":15,"curve":[0.25,0,0.75,1],"rotate":-9.48},{"duration":0}]},{"name":"wuqi3","rotateFrame":[{"duration":30,"rotate":-32.13}]},{"name":"paopao2","scaleFrame":[{"duration":7,"curve":[0.378,0.52,0.748,1],"x":0.77,"y":0.77},{"duration":15,"curve":[0.25,0,0.75,1],"x":0.58,"y":0.58},{"duration":8,"curve":[0.25,0,1,1]},{"duration":0,"x":0.77,"y":0.77}]}],"slot":[{"name":"03","displayFrame":[{"duration":30}]},{"name":"08","displayFrame":[{"duration":30}]},{"name":"18","displayFrame":[{"duration":30}]},{"name":"19","displayFrame":[{"duration":30}]},{"name":"24","displayFrame":[{"duration":30}]},{"name":"paopao2","displayFrame":[{"duration":30}]},{"name":"wuqi1","displayFrame":[{"duration":30,"value":-1}]},{"name":"wuqi3","displayFrame":[{"duration":30}]},{"name":"wuqi2","displayFrame":[{"duration":30,"value":-1}]}],"zOrder":{"frame":[{"duration":30,"zOrder":[3,10,4,10,5,10,6,10]}]}},{"duration":30,"playTimes":0,"name":"walk","bone":[{"name":"28","rotateFrame":[{"duration":15,"tweenEasing":0},{"duration":15,"tweenEasing":0,"rotate":3.3},{"duration":0}]},{"name":"bone","translateFrame":[{"duration":15,"tweenEasing":0},{"duration":15,"tweenEasing":0,"x":1.01,"y":-0.14},{"duration":0}]},{"name":"hand1","rotateFrame":[{"duration":15,"tweenEasing":0},{"duration":15,"tweenEasing":0,"rotate":3.11},{"duration":0}]},{"name":"hand","rotateFrame":[{"duration":15,"tweenEasing":0},{"duration":15,"tweenEasing":0,"rotate":-3.11},{"duration":0}]},{"name":"bone7","rotateFrame":[{"duration":15,"tweenEasing":0},{"duration":15,"tweenEasing":0,"rotate":3.05},{"duration":0}]},{"name":"bone5","rotateFrame":[{"duration":15,"tweenEasing":0},{"duration":15,"tweenEasing":0,"rotate":-5.3},{"duration":0}]},{"name":"31","translateFrame":[{"duration":7,"tweenEasing":0},{"duration":8,"tweenEasing":0,"x":2.61,"y":-3.63},{"duration":15,"tweenEasing":0,"x":4.2,"y":-0.52},{"duration":0}],"rotateFrame":[{"duration":15,"tweenEasing":0},{"duration":15,"tweenEasing":0,"rotate":-34.83},{"duration":0}]},{"name":"20","translateFrame":[{"duration":15,"tweenEasing":0},{"duration":7,"tweenEasing":0,"x":-1.39},{"duration":8,"tweenEasing":0,"x":-0.78,"y":-2.69},{"duration":0}],"rotateFrame":[{"duration":15,"tweenEasing":0,"rotate":-13.62},{"duration":15,"tweenEasing":0,"rotate":26.91},{"duration":0,"rotate":-13.62}]}]},{"duration":30,"name":"idle_3_1","bone":[{"name":"bone","translateFrame":[{"duration":15,"curve":[0,0,0.75,1]},{"duration":15,"tweenEasing":0,"x":1.14,"y":-0.16},{"duration":0}]},{"name":"hand","rotateFrame":[{"duration":30,"rotate":30.48}]},{"name":"bone2","rotateFrame":[{"duration":30,"rotate":-5.59}]},{"name":"24","translateFrame":[{"duration":30,"x":4.88,"y":0.86}],"rotateFrame":[{"duration":30,"rotate":-23.15}]},{"name":"bone30","rotateFrame":[{"duration":30,"rotate":-98.31}]},{"name":"28","rotateFrame":[{"duration":15,"curve":[0.25,0,0.75,1]},{"duration":15,"tweenEasing":0,"rotate":3.77},{"duration":0}]},{"name":"bone5","rotateFrame":[{"duration":15,"tweenEasing":0},{"duration":15,"tweenEasing":0,"rotate":-5.78},{"duration":0}]},{"name":"bone7","rotateFrame":[{"duration":15,"tweenEasing":0},{"duration":15,"tweenEasing":0,"rotate":2.98},{"duration":0}]}],"slot":[{"name":"03","displayFrame":[{"duration":30}]},{"name":"18","displayFrame":[{"duration":30}]},{"name":"19","displayFrame":[{"duration":30}]},{"name":"24","displayFrame":[{"duration":30}]},{"name":"wuqi1","displayFrame":[{"duration":30,"value":-1}]},{"name":"wuqi3","displayFrame":[{"duration":30}]},{"name":"wuqi2","displayFrame":[{"duration":30,"value":-1}]}],"zOrder":{"frame":[{"duration":30,"zOrder":[3,9,4,9,5,9,6,9]}]}},{"duration":30,"playTimes":0,"name":"idle_1_1","bone":[{"name":"28","rotateFrame":[{"duration":15,"tweenEasing":0},{"duration":15,"tweenEasing":0,"rotate":3.3},{"duration":0}]},{"name":"bone","translateFrame":[{"duration":15,"tweenEasing":0},{"duration":15,"tweenEasing":0,"x":1.01,"y":-0.14},{"duration":0}]},{"name":"hand1","rotateFrame":[{"duration":15,"tweenEasing":0},{"duration":15,"tweenEasing":0,"rotate":3.11},{"duration":0}]},{"name":"hand","rotateFrame":[{"duration":15,"tweenEasing":0},{"duration":15,"tweenEasing":0,"rotate":-3.11},{"duration":0}]},{"name":"bone7","rotateFrame":[{"duration":15,"tweenEasing":0},{"duration":15,"tweenEasing":0,"rotate":3.05},{"duration":0}]},{"name":"bone5","rotateFrame":[{"duration":15,"tweenEasing":0},{"duration":15,"tweenEasing":0,"rotate":-5.3},{"duration":0}]}]}],"defaultActions":[{"gotoAndPlay":"attack_1"}]}]}